fcm_send/__init__.py
fcm_send/__main__.py
fcm_send/__version__.py
fcm_send/cli.py
fcm_send/client.py
fcm_send/py.typed
fcm_send-0.1.1.dist-info/METADATA
fcm_send-0.1.1.dist-info/WHEEL
fcm_send-0.1.1.dist-info/entry_points.txt
fcm_send-0.1.1.dist-info/licenses/LICENSE
fcm_send-0.1.1.dist-info/RECORD
