Metadata-Version: 2.4
Name: fcm-send
Version: 0.1.1
Summary: A Python CLI tool for sending Firebase Cloud Messaging (FCM) notifications
License-Expression: MIT
License-File: LICENSE
Keywords: firebase,fcm,push-notifications,cloud-messaging,notifications,cli
Author: Felipe Ferreira
Author-email: mfelipeof@gmail.com
Requires-Python: >=3.9,<4.0
Classifier: Development Status :: 4 - Beta
Classifier: Environment :: Console
Classifier: Intended Audience :: Developers
Classifier: License :: OSI Approved :: MIT License
Classifier: Operating System :: OS Independent
Classifier: Programming Language :: Python :: 3
Classifier: Programming Language :: Python :: 3.9
Classifier: Programming Language :: Python :: 3.10
Classifier: Programming Language :: Python :: 3.11
Classifier: Programming Language :: Python :: 3.12
Classifier: Programming Language :: Python :: 3.13
Classifier: Topic :: Communications
Classifier: Topic :: Software Development :: Libraries :: Python Modules
Classifier: Topic :: Utilities
Provides-Extra: dev
Requires-Dist: build (>=1.0.0) ; extra == "dev"
Requires-Dist: firebase-admin (>=6.0.0)
Requires-Dist: pylint (>=3.0.0) ; extra == "dev"
Requires-Dist: pytest (>=7.0.0) ; extra == "dev"
Requires-Dist: pytest-cov (>=4.0.0) ; extra == "dev"
Requires-Dist: twine (>=5.0.0) ; extra == "dev"
Project-URL: Documentation, https://github.com/mfdeveloper/firebase_cloud_messaging_cli#readme
Project-URL: Homepage, https://github.com/mfdeveloper/firebase_cloud_messaging_cli
Project-URL: Issues, https://github.com/mfdeveloper/firebase_cloud_messaging_cli/issues
Project-URL: Repository, https://github.com/mfdeveloper/firebase_cloud_messaging_cli
